{
  "generated_at": 1783285843,
  "embedding_model": "nomic-ai/nomic-embed-text-v1.5",
  "collection": "robinhood",
  "domains": [
    {
      "name": "robinhood",
      "description": "Robinhood Chain tokenized-stock market \u2014 live asset snapshots + notable on-chain transfer flow",
      "count": 37632,
      "dim": 256,
      "bytes": 173452273,
      "shard_count": 24,
      "entity_types": [
        "Transfer",
        "Asset"
      ],
      "manifest": "robinhood/manifest.json",
      "edge_count": 51007,
      "relations": [
        "hasTransfer",
        "receivedBy",
        "sentBy"
      ]
    }
  ]
}